{
  "title": "跨境保险通2.0来了！港险配置正当时",
  "duration": "60秒",
  "structure": {
    "opening": {
      "duration": "5秒",
      "script": "跨境保险通2.0正式启动，大湾区9城可以直接投保香港保险了！"
    },
    "body": {
      "topic1": {
        "duration": "15秒",
        "script": "这次2.0最大的变化是——医疗险和重疾险也能在家门口买了，不用再专门跑香港。而且CAR-T免疫疗法这种癌症治疗黑科技，已经全面纳入香港重疾险保障范围。"
      },
      "topic2": {
        "duration": "15秒",
        "script": "数据显示，今年Q1内地客赴港投保新单保费按年大涨38%，聪明人已经在行动了。恒生指数维持在23000点，宏观环境也很稳健。"
      },
      "topic3": {
        "duration": "15秒",
        "script": "作为独立理财顾问，我建议重点关注储蓄险加医疗险的组合配置。选择产品时重点看保证回本时间和IRR预期收益，当然分散货币风险也很重要。"
      }
    },
    "warning": {
      "duration": "5秒",
      "script": "记住，IRR是预期收益非保证，详细条款要以保险公司合同为准。"
    },
    "cta": {
      "duration": "5秒",
      "script": "想了解适合你的港险配置方案？评论区扣【港险】，我发给你。"
    }
  },
  "visual_notes": [
    "开场：香港城市天际线",
    "过渡：保险通2.0政策解读字幕",
    "高潮：CAR-T免疫疗法示意图",
    "结尾：产品对比图表"
  ],
  "hashtags": ["跨境保险通", "香港保险", "大湾区保险", "重疾险", "医疗险", "CAR_T", "IFA", "理财"]
}
